annea_bar/__init__.py
annea_bar/example.py
annea_bar-0.1.63.dist-info/METADATA
annea_bar-0.1.63.dist-info/WHEEL
annea_bar-0.1.63.dist-info/top_level.txt
annea_bar-0.1.63.dist-info/RECORD
